__init__.py
anl2025/__init__.py
anl2025/cli.py
anl2025/common.py
anl2025/inout.py
anl2025/negotiator.py
anl2025/runner.py
anl2025/scenario.py
anl2025/tournament.py
anl2025/ufun.py
anl2025/example_scenarios/.DS_Store
anl2025/example_scenarios/Version_march17.txt
anl2025/example_scenarios/Dinners/center.csv
anl2025/example_scenarios/Dinners/center.yml
anl2025/example_scenarios/Dinners/dinners_center.py
anl2025/example_scenarios/Dinners/edges/edge001.yml
anl2025/example_scenarios/Dinners/edges/edge002.yml
anl2025/example_scenarios/Dinners/edges/edge003.yml
anl2025/example_scenarios/JobHunt/center.yml
anl2025/example_scenarios/JobHunt/edges/employee1.yml
anl2025/example_scenarios/JobHunt/edges/employee2.yml
anl2025/example_scenarios/JobHunt/edges/employee3.yml
anl2025/example_scenarios/JobHunt/edges/employee4.yml
anl2025/example_scenarios/TargetQuantity/.DS_Store
anl2025/example_scenarios/TargetQuantity/center.csv
anl2025/example_scenarios/TargetQuantity/center.yml
anl2025/example_scenarios/TargetQuantity/tq_center.py
anl2025/example_scenarios/TargetQuantity/edges/edge001.yml
anl2025/example_scenarios/TargetQuantity/edges/edge002.yml
anl2025/example_scenarios/TargetQuantity/edges/edge003.yml
anl2025/example_scenarios/TargetQuantity/edges/edge004.yml
anl2025/scenarios/__init__.py
anl2025/scenarios/dinners.py
anl2025/scenarios/job_hunt.py
anl2025/scenarios/target_quantity.py
anl2025-0.1.6.dist-info/METADATA
anl2025-0.1.6.dist-info/WHEEL
anl2025-0.1.6.dist-info/entry_points.txt
anl2025-0.1.6.dist-info/top_level.txt
anl2025-0.1.6.dist-info/RECORD
