Metadata-Version: 2.4
Name: anl2025
Version: 0.1.6
Summary: Temporary development of anl2025
Requires-Python: ~=3.11
Requires-Dist: negmas>=0.11.3
Requires-Dist: typer>=0.12.5
Requires-Dist: multiprocess>=0.70.17
Provides-Extra: doc
Requires-Dist: jupyter>=1.1.1; extra == "doc"
Requires-Dist: mkdocs-include-markdown-plugin>=7.1.4; extra == "doc"
Requires-Dist: mkdocs-material>=9.6.4; extra == "doc"
Requires-Dist: mkdocs>=1.6.1; extra == "doc"
Requires-Dist: mkdocstrings-python>=1.16.0; extra == "doc"
Requires-Dist: mkdocstrings>=0.28.1; extra == "doc"
Provides-Extra: anl2024
Requires-Dist: anl>=0.1.13; extra == "anl2024"
Requires-Dist: anl-agents>=0.1.1; extra == "anl2024"
Provides-Extra: dev
Requires-Dist: pre-commit>=4.2.0; extra == "dev"
Requires-Dist: hypothesis>=6.118.8; extra == "dev"
Requires-Dist: pytest>=8.3.3; extra == "dev"
Requires-Dist: jupyter>=1.1.1; extra == "dev"
